pygray3/__init__.py
pygray3/extensions/__init__.py
pygray3/extensions/key.c
pygray3/extensions/key.cp39-win_amd64.pyd
pygray3/extensions/key.pyi
pygray3/extensions/libapi.dll
pygray3-0.5.dist-info/METADATA
pygray3-0.5.dist-info/WHEEL
pygray3-0.5.dist-info/top_level.txt
pygray3-0.5.dist-info/RECORD
